afterpay/__init__.py
afterpay/attribute_getter.py
afterpay/client_token.py
afterpay/client_token_gateway.py
afterpay/configuration.py
afterpay/consumer.py
afterpay/contact.py
afterpay/environment.py
afterpay/gateway.py
afterpay/merchant.py
afterpay/money.py
afterpay/payment.py
afterpay/version.py
afterpay/exceptions/__init__.py
afterpay/exceptions/afterpay_error.py
afterpay/exceptions/authentication_error.py
afterpay/exceptions/configuration_error.py
afterpay/exceptions/invalid_headers.py
afterpay/exceptions/invalid_method.py
afterpay/exceptions/invalid_request.py
afterpay/exceptions/params_error.py
afterpay/exceptions/payment_error.py
afterpay/exceptions/payment_not_found_error.py
afterpay/exceptions/server_error.py
afterpay/exceptions/token_error.py
afterpay/exceptions/unexpected_error.py
afterpay/exceptions/http/__init__.py
afterpay/exceptions/http/connection_error.py
afterpay/exceptions/http/invalid_response_error.py
afterpay/exceptions/http/timeout_error.py
afterpay/util/__init__.py
afterpay/util/http.py
afterpay-0.4.0.dist-info/LICENSE
afterpay-0.4.0.dist-info/METADATA
afterpay-0.4.0.dist-info/WHEEL
afterpay-0.4.0.dist-info/top_level.txt
afterpay-0.4.0.dist-info/RECORD
