Metadata-Version: 2.1
Name: afterpay
Version: 0.4.0
Summary: Python library for interacting with Afterpay API
Home-page: https://github.com/nyneava/afterpay-python
Author: nyneava
Author-email: nyneava@gmail.com
License: UNKNOWN
Platform: UNKNOWN
Classifier: Programming Language :: Python :: 3
Classifier: License :: OSI Approved :: MIT License
Classifier: Operating System :: OS Independent
License-File: LICENSE
